<?xml version="1.0" encoding="UTF-8"?>
<!-- Product Version: Vivado v2023.1 (64-bit)                                     -->
<!--                                                                              -->
<!-- Copyright 1986-2022 Xilinx, Inc. All Rights Reserved.                        -->
<!-- Copyright 2022-2023 Advanced Micro Devices, Inc. All Rights Reserved.        -->

<hwsession version="1" minor="2">
  <device name="xc7z010_1" gui_info="dashboard1=hw_ila_1[xc7z010_1/hw_ila_1/Settings=ILA_SETTINGS_1;xc7z010_1/hw_ila_1/Status=ILA_STATUS_1;xc7z010_1/hw_ila_1/Capture Setup=ILA_CAPTURE_1;xc7z010_1/hw_ila_1/Waveform=ILA_WAVE_1;xc7z010_1/hw_ila_1/Trigger Setup=ILA_TRIGGER_1;]"/>
  <ObjectList object_type="hw_device" gui_info="">
    <Object name="xc7z010_1" gui_info="">
      <Properties Property="FULL_PROBES.FILE" value="$_project_name_.runs/impl_1/modulo_display.ltx"/>
      <Properties Property="PROBES.FILE" value="$_project_name_.runs/impl_1/modulo_display.ltx"/>
      <Properties Property="PROGRAM.HW_BITSTREAM" value="$_project_name_.runs/impl_1/modulo_display.bit"/>
      <Properties Property="SLR.COUNT" value="1"/>
    </Object>
  </ObjectList>
  <ObjectList object_type="hw_ila" gui_info="">
    <Object name="" gui_info="">
      <Properties Property="CONTROL.TRIGGER_CONDITION" value="AND"/>
      <Properties Property="CORE_REFRESH_RATE_MS" value="500"/>
    </Object>
    <Object name="u_ila_0" gui_info="">
      <Properties Property="CONTROL.TRIGGER_CONDITION" value="AND"/>
      <Properties Property="CORE_REFRESH_RATE_MS" value="500"/>
    </Object>
  </ObjectList>
  <probeset name="hw project" active="false">
    <probe type="ila" busType="bus" source="netlist" spec="ILA_V2_RT">
      <probeOptions Id="DebugProbeParams">
        <Option Id="CAPTURE_COMPARE_VALUE" value="eq3&apos;hX"/>
        <Option Id="COMPARE_VALUE.0" value="eq3&apos;hX"/>
        <Option Id="DISPLAY_AS_ENUM" value="1"/>
        <Option Id="DISPLAY_HINT" value=""/>
        <Option Id="DISPLAY_RADIX" value="HEX"/>
        <Option Id="DISPLAY_VISIBILITY" value=""/>
        <Option Id="HW_ILA" value="hw_ila_1"/>
        <Option Id="LINK_TO_WAVEFORM" value="1"/>
        <Option Id="MAP" value="probe0[2:0]"/>
        <Option Id="NAME.CUSTOM" value=""/>
        <Option Id="NAME.SELECT" value="Long"/>
        <Option Id="SOURCE" value="netlist"/>
        <Option Id="TRIGGER_COMPARE_VALUE" value="eq3&apos;hX"/>
        <Option Id="WAVEFORM_STYLE" value="Digital"/>
      </probeOptions>
      <nets>
        <net name="B_OBUF[2]"/>
        <net name="B_OBUF[1]"/>
        <net name="B_OBUF[0]"/>
      </nets>
    </probe>
    <probe type="ila" busType="bus" source="netlist" spec="ILA_V2_RT">
      <probeOptions Id="DebugProbeParams">
        <Option Id="CAPTURE_COMPARE_VALUE" value="eq2&apos;hX"/>
        <Option Id="COMPARE_VALUE.0" value="eq2&apos;hX"/>
        <Option Id="DISPLAY_AS_ENUM" value="1"/>
        <Option Id="DISPLAY_HINT" value=""/>
        <Option Id="DISPLAY_RADIX" value="HEX"/>
        <Option Id="DISPLAY_VISIBILITY" value=""/>
        <Option Id="HW_ILA" value="hw_ila_1"/>
        <Option Id="LINK_TO_WAVEFORM" value="1"/>
        <Option Id="MAP" value="probe1[1:0]"/>
        <Option Id="NAME.CUSTOM" value=""/>
        <Option Id="NAME.SELECT" value="Long"/>
        <Option Id="SOURCE" value="netlist"/>
        <Option Id="TRIGGER_COMPARE_VALUE" value="eq2&apos;hX"/>
        <Option Id="WAVEFORM_STYLE" value="Digital"/>
      </probeOptions>
      <nets>
        <net name="D_in[1]"/>
        <net name="D_in[0]"/>
      </nets>
    </probe>
    <probe type="ila" busType="bus" source="netlist" spec="ILA_V2_RT">
      <probeOptions Id="DebugProbeParams">
        <Option Id="CAPTURE_COMPARE_VALUE" value="eq2&apos;hX"/>
        <Option Id="COMPARE_VALUE.0" value="eq2&apos;hX"/>
        <Option Id="DISPLAY_AS_ENUM" value="1"/>
        <Option Id="DISPLAY_HINT" value=""/>
        <Option Id="DISPLAY_RADIX" value="HEX"/>
        <Option Id="DISPLAY_VISIBILITY" value=""/>
        <Option Id="HW_ILA" value="hw_ila_1"/>
        <Option Id="LINK_TO_WAVEFORM" value="1"/>
        <Option Id="MAP" value="probe2[1:0]"/>
        <Option Id="NAME.CUSTOM" value=""/>
        <Option Id="NAME.SELECT" value="Long"/>
        <Option Id="SOURCE" value="netlist"/>
        <Option Id="TRIGGER_COMPARE_VALUE" value="eq2&apos;hX"/>
        <Option Id="WAVEFORM_STYLE" value="Digital"/>
      </probeOptions>
      <nets>
        <net name="D_out[1]"/>
        <net name="D_out[0]"/>
      </nets>
    </probe>
    <probe type="ila" busType="net" source="netlist" spec="ILA_V2_RT">
      <probeOptions Id="DebugProbeParams">
        <Option Id="CAPTURE_COMPARE_VALUE" value="eq1&apos;bX"/>
        <Option Id="COMPARE_VALUE.0" value="eq1&apos;bX"/>
        <Option Id="DISPLAY_AS_ENUM" value="1"/>
        <Option Id="DISPLAY_HINT" value=""/>
        <Option Id="DISPLAY_RADIX" value="HEX"/>
        <Option Id="DISPLAY_VISIBILITY" value=""/>
        <Option Id="HW_ILA" value="hw_ila_1"/>
        <Option Id="LINK_TO_WAVEFORM" value="1"/>
        <Option Id="MAP" value="probe5[0]"/>
        <Option Id="NAME.CUSTOM" value=""/>
        <Option Id="NAME.SELECT" value="Long"/>
        <Option Id="SOURCE" value="netlist"/>
        <Option Id="TRIGGER_COMPARE_VALUE" value="eq1&apos;bX"/>
        <Option Id="WAVEFORM_STYLE" value="Digital"/>
      </probeOptions>
      <nets>
        <net name="clk_IBUF_BUFG"/>
      </nets>
    </probe>
    <probe type="ila" busType="bus" source="netlist" spec="ILA_V2_RT">
      <probeOptions Id="DebugProbeParams">
        <Option Id="CAPTURE_COMPARE_VALUE" value="eq4&apos;hX"/>
        <Option Id="COMPARE_VALUE.0" value="eq4&apos;hX"/>
        <Option Id="DISPLAY_AS_ENUM" value="1"/>
        <Option Id="DISPLAY_HINT" value=""/>
        <Option Id="DISPLAY_RADIX" value="HEX"/>
        <Option Id="DISPLAY_VISIBILITY" value=""/>
        <Option Id="HW_ILA" value="hw_ila_1"/>
        <Option Id="LINK_TO_WAVEFORM" value="1"/>
        <Option Id="MAP" value="probe3[3:0]"/>
        <Option Id="NAME.CUSTOM" value=""/>
        <Option Id="NAME.SELECT" value="Long"/>
        <Option Id="SOURCE" value="netlist"/>
        <Option Id="TRIGGER_COMPARE_VALUE" value="eq4&apos;hX"/>
        <Option Id="WAVEFORM_STYLE" value="Digital"/>
      </probeOptions>
      <nets>
        <net name="cols_OBUF[3]"/>
        <net name="cols_OBUF[2]"/>
        <net name="cols_OBUF[1]"/>
        <net name="cols_OBUF[0]"/>
      </nets>
    </probe>
    <probe type="ila" busType="net" source="netlist" spec="ILA_V2_RT">
      <probeOptions Id="DebugProbeParams">
        <Option Id="CAPTURE_COMPARE_VALUE" value="eq4&apos;hX"/>
        <Option Id="COMPARE_VALUE.0" value="eq4&apos;hX"/>
        <Option Id="DISPLAY_AS_ENUM" value="1"/>
        <Option Id="DISPLAY_HINT" value=""/>
        <Option Id="DISPLAY_RADIX" value="HEX"/>
        <Option Id="DISPLAY_VISIBILITY" value=""/>
        <Option Id="HW_ILA" value="hw_ila_1"/>
        <Option Id="LINK_TO_WAVEFORM" value="1"/>
        <Option Id="MAP" value="probe1[3:0]"/>
        <Option Id="NAME.CUSTOM" value=""/>
        <Option Id="NAME.SELECT" value="Long"/>
        <Option Id="SOURCE" value="netlist"/>
        <Option Id="TRIGGER_COMPARE_VALUE" value="eq4&apos;hX"/>
        <Option Id="WAVEFORM_STYLE" value="Digital"/>
      </probeOptions>
      <nets>
        <net name="decoteclado1/deco1/cols[3]"/>
        <net name="decoteclado1/deco1/cols[2]"/>
        <net name="decoteclado1/deco1/cols[1]"/>
        <net name="decoteclado1/deco1/cols[0]"/>
      </nets>
    </probe>
    <probe type="ila" busType="net" source="netlist" spec="ILA_V2_RT">
      <probeOptions Id="DebugProbeParams">
        <Option Id="CAPTURE_COMPARE_VALUE" value="eq1&apos;bX"/>
        <Option Id="COMPARE_VALUE.0" value="eq1&apos;bX"/>
        <Option Id="DISPLAY_AS_ENUM" value="1"/>
        <Option Id="DISPLAY_HINT" value=""/>
        <Option Id="DISPLAY_RADIX" value="HEX"/>
        <Option Id="DISPLAY_VISIBILITY" value=""/>
        <Option Id="HW_ILA" value="hw_ila_1"/>
        <Option Id="LINK_TO_WAVEFORM" value="1"/>
        <Option Id="MAP" value="probe5[0]"/>
        <Option Id="NAME.CUSTOM" value=""/>
        <Option Id="NAME.SELECT" value="Long"/>
        <Option Id="SOURCE" value="netlist"/>
        <Option Id="TRIGGER_COMPARE_VALUE" value="eq1&apos;bX"/>
        <Option Id="WAVEFORM_STYLE" value="Digital"/>
      </probeOptions>
      <nets>
        <net name="decoteclado1/deco1/n_0_0"/>
      </nets>
    </probe>
    <probe type="ila" busType="net" source="netlist" spec="ILA_V2_RT">
      <probeOptions Id="DebugProbeParams">
        <Option Id="CAPTURE_COMPARE_VALUE" value="eq1&apos;bX"/>
        <Option Id="COMPARE_VALUE.0" value="eq1&apos;bX"/>
        <Option Id="DISPLAY_AS_ENUM" value="1"/>
        <Option Id="DISPLAY_HINT" value=""/>
        <Option Id="DISPLAY_RADIX" value="HEX"/>
        <Option Id="DISPLAY_VISIBILITY" value=""/>
        <Option Id="HW_ILA" value="hw_ila_1"/>
        <Option Id="LINK_TO_WAVEFORM" value="1"/>
        <Option Id="MAP" value="probe6[0]"/>
        <Option Id="NAME.CUSTOM" value=""/>
        <Option Id="NAME.SELECT" value="Long"/>
        <Option Id="SOURCE" value="netlist"/>
        <Option Id="TRIGGER_COMPARE_VALUE" value="eq1&apos;bX"/>
        <Option Id="WAVEFORM_STYLE" value="Digital"/>
      </probeOptions>
      <nets>
        <net name="decoteclado1/deco1/n_0_1"/>
      </nets>
    </probe>
    <probe type="ila" busType="net" source="netlist" spec="ILA_V2_RT">
      <probeOptions Id="DebugProbeParams">
        <Option Id="CAPTURE_COMPARE_VALUE" value="eq1&apos;bX"/>
        <Option Id="COMPARE_VALUE.0" value="eq1&apos;bX"/>
        <Option Id="DISPLAY_AS_ENUM" value="1"/>
        <Option Id="DISPLAY_HINT" value=""/>
        <Option Id="DISPLAY_RADIX" value="HEX"/>
        <Option Id="DISPLAY_VISIBILITY" value=""/>
        <Option Id="HW_ILA" value="hw_ila_1"/>
        <Option Id="LINK_TO_WAVEFORM" value="1"/>
        <Option Id="MAP" value="probe7[0]"/>
        <Option Id="NAME.CUSTOM" value=""/>
        <Option Id="NAME.SELECT" value="Long"/>
        <Option Id="SOURCE" value="netlist"/>
        <Option Id="TRIGGER_COMPARE_VALUE" value="eq1&apos;bX"/>
        <Option Id="WAVEFORM_STYLE" value="Digital"/>
      </probeOptions>
      <nets>
        <net name="decoteclado1/deco1/n_0_2"/>
      </nets>
    </probe>
    <probe type="ila" busType="net" source="netlist" spec="ILA_V2_RT">
      <probeOptions Id="DebugProbeParams">
        <Option Id="CAPTURE_COMPARE_VALUE" value="eq1&apos;bX"/>
        <Option Id="COMPARE_VALUE.0" value="eq1&apos;bX"/>
        <Option Id="DISPLAY_AS_ENUM" value="1"/>
        <Option Id="DISPLAY_HINT" value=""/>
        <Option Id="DISPLAY_RADIX" value="HEX"/>
        <Option Id="DISPLAY_VISIBILITY" value=""/>
        <Option Id="HW_ILA" value="hw_ila_1"/>
        <Option Id="LINK_TO_WAVEFORM" value="1"/>
        <Option Id="MAP" value="probe8[0]"/>
        <Option Id="NAME.CUSTOM" value=""/>
        <Option Id="NAME.SELECT" value="Long"/>
        <Option Id="SOURCE" value="netlist"/>
        <Option Id="TRIGGER_COMPARE_VALUE" value="eq1&apos;bX"/>
        <Option Id="WAVEFORM_STYLE" value="Digital"/>
      </probeOptions>
      <nets>
        <net name="decoteclado1/deco1/n_0_3"/>
      </nets>
    </probe>
    <probe type="ila" busType="net" source="netlist" spec="ILA_V2_RT">
      <probeOptions Id="DebugProbeParams">
        <Option Id="CAPTURE_COMPARE_VALUE" value="eq4&apos;hX"/>
        <Option Id="COMPARE_VALUE.0" value="eq4&apos;hX"/>
        <Option Id="DISPLAY_AS_ENUM" value="1"/>
        <Option Id="DISPLAY_HINT" value=""/>
        <Option Id="DISPLAY_RADIX" value="HEX"/>
        <Option Id="DISPLAY_VISIBILITY" value=""/>
        <Option Id="HW_ILA" value="hw_ila_1"/>
        <Option Id="LINK_TO_WAVEFORM" value="1"/>
        <Option Id="MAP" value="probe0[3:0]"/>
        <Option Id="NAME.CUSTOM" value=""/>
        <Option Id="NAME.SELECT" value="Long"/>
        <Option Id="SOURCE" value="netlist"/>
        <Option Id="TRIGGER_COMPARE_VALUE" value="eq4&apos;hX"/>
        <Option Id="WAVEFORM_STYLE" value="Digital"/>
      </probeOptions>
      <nets>
        <net name="decoteclado1/deco1/rows[3]"/>
        <net name="decoteclado1/deco1/rows[2]"/>
        <net name="decoteclado1/deco1/rows[1]"/>
        <net name="decoteclado1/deco1/rows[0]"/>
      </nets>
    </probe>
    <probe type="ila" busType="net" source="netlist" spec="ILA_V2_RT">
      <probeOptions Id="DebugProbeParams">
        <Option Id="CAPTURE_COMPARE_VALUE" value="eq4&apos;hX"/>
        <Option Id="COMPARE_VALUE.0" value="eq4&apos;hX"/>
        <Option Id="DISPLAY_AS_ENUM" value="1"/>
        <Option Id="DISPLAY_HINT" value=""/>
        <Option Id="DISPLAY_RADIX" value="HEX"/>
        <Option Id="DISPLAY_VISIBILITY" value=""/>
        <Option Id="HW_ILA" value="hw_ila_1"/>
        <Option Id="LINK_TO_WAVEFORM" value="1"/>
        <Option Id="MAP" value="probe2[3:0]"/>
        <Option Id="NAME.CUSTOM" value=""/>
        <Option Id="NAME.SELECT" value="Long"/>
        <Option Id="SOURCE" value="netlist"/>
        <Option Id="TRIGGER_COMPARE_VALUE" value="eq4&apos;hX"/>
        <Option Id="WAVEFORM_STYLE" value="Digital"/>
      </probeOptions>
      <nets>
        <net name="decoteclado1/fsm1/next_state[3]"/>
        <net name="decoteclado1/fsm1/next_state[2]"/>
        <net name="decoteclado1/fsm1/next_state[1]"/>
        <net name="decoteclado1/fsm1/next_state[0]"/>
      </nets>
    </probe>
    <probe type="ila" busType="net" source="netlist" spec="ILA_V2_RT">
      <probeOptions Id="DebugProbeParams">
        <Option Id="CAPTURE_COMPARE_VALUE" value="eq4&apos;hX"/>
        <Option Id="COMPARE_VALUE.0" value="eq4&apos;hX"/>
        <Option Id="DISPLAY_AS_ENUM" value="1"/>
        <Option Id="DISPLAY_HINT" value=""/>
        <Option Id="DISPLAY_RADIX" value="HEX"/>
        <Option Id="DISPLAY_VISIBILITY" value=""/>
        <Option Id="HW_ILA" value="hw_ila_1"/>
        <Option Id="LINK_TO_WAVEFORM" value="1"/>
        <Option Id="MAP" value="probe3[3:0]"/>
        <Option Id="NAME.CUSTOM" value=""/>
        <Option Id="NAME.SELECT" value="Long"/>
        <Option Id="SOURCE" value="netlist"/>
        <Option Id="TRIGGER_COMPARE_VALUE" value="eq4&apos;hX"/>
        <Option Id="WAVEFORM_STYLE" value="Digital"/>
      </probeOptions>
      <nets>
        <net name="decoteclado1/fsm1/state[3]"/>
        <net name="decoteclado1/fsm1/state[2]"/>
        <net name="decoteclado1/fsm1/state[1]"/>
        <net name="decoteclado1/fsm1/state[0]"/>
      </nets>
    </probe>
    <probe type="ila" busType="net" source="netlist" spec="ILA_V2_RT">
      <probeOptions Id="DebugProbeParams">
        <Option Id="CAPTURE_COMPARE_VALUE" value="eq5&apos;hXX"/>
        <Option Id="COMPARE_VALUE.0" value="eq5&apos;hXX"/>
        <Option Id="DISPLAY_AS_ENUM" value="1"/>
        <Option Id="DISPLAY_HINT" value=""/>
        <Option Id="DISPLAY_RADIX" value="HEX"/>
        <Option Id="DISPLAY_VISIBILITY" value=""/>
        <Option Id="HW_ILA" value="hw_ila_1"/>
        <Option Id="LINK_TO_WAVEFORM" value="1"/>
        <Option Id="MAP" value="probe4[4:0]"/>
        <Option Id="NAME.CUSTOM" value=""/>
        <Option Id="NAME.SELECT" value="Long"/>
        <Option Id="SOURCE" value="netlist"/>
        <Option Id="TRIGGER_COMPARE_VALUE" value="eq5&apos;hXX"/>
        <Option Id="WAVEFORM_STYLE" value="Digital"/>
      </probeOptions>
      <nets>
        <net name="decoteclado1/key[4]"/>
        <net name="decoteclado1/key[3]"/>
        <net name="decoteclado1/key[2]"/>
        <net name="decoteclado1/key[1]"/>
        <net name="decoteclado1/key[0]"/>
      </nets>
    </probe>
    <probe type="ila" busType="net" source="netlist" spec="ILA_V2_RT">
      <probeOptions Id="DebugProbeParams">
        <Option Id="CAPTURE_COMPARE_VALUE" value="eq1&apos;bX"/>
        <Option Id="COMPARE_VALUE.0" value="eq1&apos;bX"/>
        <Option Id="DISPLAY_AS_ENUM" value="1"/>
        <Option Id="DISPLAY_HINT" value=""/>
        <Option Id="DISPLAY_RADIX" value="HEX"/>
        <Option Id="DISPLAY_VISIBILITY" value=""/>
        <Option Id="HW_ILA" value="hw_ila_1"/>
        <Option Id="LINK_TO_WAVEFORM" value="1"/>
        <Option Id="MAP" value="probe6[0]"/>
        <Option Id="NAME.CUSTOM" value=""/>
        <Option Id="NAME.SELECT" value="Long"/>
        <Option Id="SOURCE" value="netlist"/>
        <Option Id="TRIGGER_COMPARE_VALUE" value="eq1&apos;bX"/>
        <Option Id="WAVEFORM_STYLE" value="Digital"/>
      </probeOptions>
      <nets>
        <net name="decoteclado1/valid"/>
      </nets>
    </probe>
    <probe type="ila" busType="net" source="netlist" spec="ILA_V2_RT">
      <probeOptions Id="DebugProbeParams">
        <Option Id="CAPTURE_COMPARE_VALUE" value="eq1&apos;bX"/>
        <Option Id="COMPARE_VALUE.0" value="eq1&apos;bX"/>
        <Option Id="DISPLAY_AS_ENUM" value="1"/>
        <Option Id="DISPLAY_HINT" value=""/>
        <Option Id="DISPLAY_RADIX" value="HEX"/>
        <Option Id="DISPLAY_VISIBILITY" value=""/>
        <Option Id="HW_ILA" value="hw_ila_1"/>
        <Option Id="LINK_TO_WAVEFORM" value="1"/>
        <Option Id="MAP" value="probe8[0]"/>
        <Option Id="NAME.CUSTOM" value=""/>
        <Option Id="NAME.SELECT" value="Long"/>
        <Option Id="SOURCE" value="netlist"/>
        <Option Id="TRIGGER_COMPARE_VALUE" value="eq1&apos;bX"/>
        <Option Id="WAVEFORM_STYLE" value="Digital"/>
      </probeOptions>
      <nets>
        <net name="enable"/>
      </nets>
    </probe>
    <probe type="ila" busType="bus" source="netlist" spec="ILA_V2_RT">
      <probeOptions Id="DebugProbeParams">
        <Option Id="CAPTURE_COMPARE_VALUE" value="eq5&apos;hXX"/>
        <Option Id="COMPARE_VALUE.0" value="eq5&apos;hXX"/>
        <Option Id="DISPLAY_AS_ENUM" value="1"/>
        <Option Id="DISPLAY_HINT" value=""/>
        <Option Id="DISPLAY_RADIX" value="HEX"/>
        <Option Id="DISPLAY_VISIBILITY" value=""/>
        <Option Id="HW_ILA" value="hw_ila_1"/>
        <Option Id="LINK_TO_WAVEFORM" value="1"/>
        <Option Id="MAP" value="probe4[4:0]"/>
        <Option Id="NAME.CUSTOM" value=""/>
        <Option Id="NAME.SELECT" value="Long"/>
        <Option Id="SOURCE" value="netlist"/>
        <Option Id="TRIGGER_COMPARE_VALUE" value="eq5&apos;hXX"/>
        <Option Id="WAVEFORM_STYLE" value="Digital"/>
      </probeOptions>
      <nets>
        <net name="key[4]"/>
        <net name="key[3]"/>
        <net name="key[2]"/>
        <net name="key[1]"/>
        <net name="key[0]"/>
      </nets>
    </probe>
    <probe type="ila" busType="bus" source="netlist" spec="ILA_V2_RT">
      <probeOptions Id="DebugProbeParams">
        <Option Id="CAPTURE_COMPARE_VALUE" value="eq5&apos;hXX"/>
        <Option Id="COMPARE_VALUE.0" value="eq5&apos;hXX"/>
        <Option Id="DISPLAY_AS_ENUM" value="1"/>
        <Option Id="DISPLAY_HINT" value=""/>
        <Option Id="DISPLAY_RADIX" value="HEX"/>
        <Option Id="DISPLAY_VISIBILITY" value=""/>
        <Option Id="HW_ILA" value="hw_ila_1"/>
        <Option Id="LINK_TO_WAVEFORM" value="1"/>
        <Option Id="MAP" value="probe5[4:0]"/>
        <Option Id="NAME.CUSTOM" value=""/>
        <Option Id="NAME.SELECT" value="Long"/>
        <Option Id="SOURCE" value="netlist"/>
        <Option Id="TRIGGER_COMPARE_VALUE" value="eq5&apos;hXX"/>
        <Option Id="WAVEFORM_STYLE" value="Digital"/>
      </probeOptions>
      <nets>
        <net name="rd[4]"/>
        <net name="rd[3]"/>
        <net name="rd[2]"/>
        <net name="rd[1]"/>
        <net name="rd[0]"/>
      </nets>
    </probe>
    <probe type="ila" busType="bus" source="netlist" spec="ILA_V2_RT">
      <probeOptions Id="DebugProbeParams">
        <Option Id="CAPTURE_COMPARE_VALUE" value="eq4&apos;hX"/>
        <Option Id="COMPARE_VALUE.0" value="eq4&apos;hX"/>
        <Option Id="DISPLAY_AS_ENUM" value="1"/>
        <Option Id="DISPLAY_HINT" value=""/>
        <Option Id="DISPLAY_RADIX" value="HEX"/>
        <Option Id="DISPLAY_VISIBILITY" value=""/>
        <Option Id="HW_ILA" value="hw_ila_1"/>
        <Option Id="LINK_TO_WAVEFORM" value="1"/>
        <Option Id="MAP" value="probe6[3:0]"/>
        <Option Id="NAME.CUSTOM" value=""/>
        <Option Id="NAME.SELECT" value="Long"/>
        <Option Id="SOURCE" value="netlist"/>
        <Option Id="TRIGGER_COMPARE_VALUE" value="eq4&apos;hX"/>
        <Option Id="WAVEFORM_STYLE" value="Digital"/>
      </probeOptions>
      <nets>
        <net name="rows_IBUF[3]"/>
        <net name="rows_IBUF[2]"/>
        <net name="rows_IBUF[1]"/>
        <net name="rows_IBUF[0]"/>
      </nets>
    </probe>
    <probe type="ila" busType="bus" source="netlist" spec="ILA_V2_RT">
      <probeOptions Id="DebugProbeParams">
        <Option Id="CAPTURE_COMPARE_VALUE" value="eq7&apos;hXX"/>
        <Option Id="COMPARE_VALUE.0" value="eq7&apos;hXX"/>
        <Option Id="DISPLAY_AS_ENUM" value="1"/>
        <Option Id="DISPLAY_HINT" value=""/>
        <Option Id="DISPLAY_RADIX" value="HEX"/>
        <Option Id="DISPLAY_VISIBILITY" value=""/>
        <Option Id="HW_ILA" value="hw_ila_1"/>
        <Option Id="LINK_TO_WAVEFORM" value="1"/>
        <Option Id="MAP" value="probe7[6:0]"/>
        <Option Id="NAME.CUSTOM" value=""/>
        <Option Id="NAME.SELECT" value="Long"/>
        <Option Id="SOURCE" value="netlist"/>
        <Option Id="TRIGGER_COMPARE_VALUE" value="eq7&apos;hXX"/>
        <Option Id="WAVEFORM_STYLE" value="Digital"/>
      </probeOptions>
      <nets>
        <net name="signal7_OBUF[6]"/>
        <net name="signal7_OBUF[5]"/>
        <net name="signal7_OBUF[4]"/>
        <net name="signal7_OBUF[3]"/>
        <net name="signal7_OBUF[2]"/>
        <net name="signal7_OBUF[1]"/>
        <net name="signal7_OBUF[0]"/>
      </nets>
    </probe>
    <probe type="ila" busType="net" source="netlist" spec="ILA_V2_RT">
      <probeOptions Id="DebugProbeParams">
        <Option Id="CAPTURE_COMPARE_VALUE" value="eq1&apos;bX"/>
        <Option Id="COMPARE_VALUE.0" value="eq1&apos;bX"/>
        <Option Id="DISPLAY_AS_ENUM" value="1"/>
        <Option Id="DISPLAY_HINT" value=""/>
        <Option Id="DISPLAY_RADIX" value="HEX"/>
        <Option Id="DISPLAY_VISIBILITY" value=""/>
        <Option Id="HW_ILA" value="hw_ila_1"/>
        <Option Id="LINK_TO_WAVEFORM" value="1"/>
        <Option Id="MAP" value="probe9[0]"/>
        <Option Id="NAME.CUSTOM" value=""/>
        <Option Id="NAME.SELECT" value="Long"/>
        <Option Id="SOURCE" value="netlist"/>
        <Option Id="TRIGGER_COMPARE_VALUE" value="eq1&apos;bX"/>
        <Option Id="WAVEFORM_STYLE" value="Digital"/>
      </probeOptions>
      <nets>
        <net name="str"/>
      </nets>
    </probe>
    <probe type="ila" busType="net" source="netlist" spec="ILA_V2_RT">
      <probeOptions Id="DebugProbeParams">
        <Option Id="CAPTURE_COMPARE_VALUE" value="eq1&apos;bX"/>
        <Option Id="COMPARE_VALUE.0" value="eq1&apos;bX"/>
        <Option Id="DISPLAY_AS_ENUM" value="1"/>
        <Option Id="DISPLAY_HINT" value=""/>
        <Option Id="DISPLAY_RADIX" value="HEX"/>
        <Option Id="DISPLAY_VISIBILITY" value=""/>
        <Option Id="HW_ILA" value="hw_ila_1"/>
        <Option Id="LINK_TO_WAVEFORM" value="1"/>
        <Option Id="MAP" value="probe10[0]"/>
        <Option Id="NAME.CUSTOM" value=""/>
        <Option Id="NAME.SELECT" value="Long"/>
        <Option Id="SOURCE" value="netlist"/>
        <Option Id="TRIGGER_COMPARE_VALUE" value="eq1&apos;bX"/>
        <Option Id="WAVEFORM_STYLE" value="Digital"/>
      </probeOptions>
      <nets>
        <net name="valid"/>
      </nets>
    </probe>
  </probeset>
</hwsession>
